ucc_sprite/__init__.py
ucc_sprite-0.0.5.dist-info/LICENSE
ucc_sprite-0.0.5.dist-info/METADATA
ucc_sprite-0.0.5.dist-info/WHEEL
ucc_sprite-0.0.5.dist-info/top_level.txt
ucc_sprite-0.0.5.dist-info/RECORD
