Metadata-Version: 2.1
Name: ucc-sprite
Version: 0.0.5
Summary: Sprite class for use in Pygame programs at UCC
Author-email: Casey Devet <casey.devet@sccdsb.net>
License: Copyright 2022 Casey Devet
Project-URL: Homepage, https://github.com/mrdevet/UCC-Sprite
Keywords: pygame,sprite,ucc
Classifier: License :: OSI Approved :: MIT License
Classifier: Programming Language :: Python :: 3
Requires-Python: >=3
License-File: LICENSE
Requires-Dist: pygame >=2.1.2
